pyQi/__init__.py
pyQi/pyQi_api.py
pyQi/pyQi_api_async.py
pyQi/samples.json
pyQi/xltojson.py
pyqi_api-1.0.4.dist-info/LICENSE.md
pyqi_api-1.0.4.dist-info/METADATA
pyqi_api-1.0.4.dist-info/WHEEL
pyqi_api-1.0.4.dist-info/top_level.txt
pyqi_api-1.0.4.dist-info/RECORD
