Metadata-Version: 2.1
Name: pyqi_api
Version: 1.0.4
Summary: Python Module for QI Content and Collections Management System by Keepthinking
Author-email: Christopher Prince <c.pj.prince@gmail.com>
Project-URL: Homepage, https://github.com/CPJPRINCE/pyqi
Project-URL: Issues, https://github.com/CPJPRINCE/pyqi/issues
Classifier: Programming Language :: Python :: 3
Classifier: License :: OSI Approved :: Apache Software License
Classifier: Operating System :: OS Independent
Classifier: Topic :: System :: Archiving
License-File: LICENSE.md
Requires-Dist: pandas
Requires-Dist: openpyxl
Requires-Dist: aiohttp
Requires-Dist: requests
